gradescope_submit.py
gradescope_submit-0.2.2.dist-info/METADATA
gradescope_submit-0.2.2.dist-info/WHEEL
gradescope_submit-0.2.2.dist-info/entry_points.txt
gradescope_submit-0.2.2.dist-info/top_level.txt
gradescope_submit-0.2.2.dist-info/RECORD
