Metadata-Version: 2.4
Name: gradescope_submit
Version: 0.2.2
Summary: Script/Module to upload assignments to Gradescope from the command line
Author-email: Chris Kauffman <kauffman77@gmail.com>
Maintainer-email: Chris Kauffman <kauffman77@gmail.com>
License-Expression: GPL-3.0-or-later
Project-URL: Homepage, https://github.com/kauffman77/gradescope-submit
Keywords: gradescope
Requires-Python: >=3.8
Requires-Dist: requests>=2.25.1
Provides-Extra: dev
Provides-Extra: test
